whisperspeech2/__init__.py
whisperspeech2/a2wav.py
whisperspeech2/inference.py
whisperspeech2/languages.py
whisperspeech2/modules.py
whisperspeech2/pipeline.py
whisperspeech2/s2a_delar_mup_wds_mlang.py
whisperspeech2/s2a_delar_mup_wds_mlang_cond.py
whisperspeech2/t2s_up_wds_mlang_enclm.py
whisperspeech2-0.9.3.dist-info/licenses/LICENSE
whisperspeech2-0.9.3.dist-info/METADATA
whisperspeech2-0.9.3.dist-info/WHEEL
whisperspeech2-0.9.3.dist-info/top_level.txt
whisperspeech2-0.9.3.dist-info/RECORD
