Metadata-Version: 2.4
Name: whisperspeech2
Version: 0.9.3
Summary: An Open Source text-to-speech system built by inverting Whisper (fork of WhisperSpeech)
Home-page: https://github.com/BBC-Esq/whisperspeech2
Author: Blair Chintella
Author-email: vici0549@gmail.com
License: MIT License
Keywords: tts text-to-speech whisper speech-synthesis
Classifier: Development Status :: 4 - Beta
Classifier: Intended Audience :: Developers
Classifier: Natural Language :: English
Classifier: Programming Language :: Python :: 3.10
Classifier: Programming Language :: Python :: 3.11
Classifier: Programming Language :: Python :: 3.12
Classifier: Programming Language :: Python :: 3.13
Classifier: License :: OSI Approved :: MIT License
Requires-Python: >=3.10
License-File: LICENSE
Requires-Dist: vocos
Requires-Dist: torch>=2
Requires-Dist: torchaudio
Requires-Dist: soundfile
Requires-Dist: huggingface_hub
Requires-Dist: fastprogress
Requires-Dist: fastcore
Requires-Dist: numpy
Provides-Extra: speaker
Requires-Dist: speechbrain<1.0; extra == "speaker"
Dynamic: author
Dynamic: author-email
Dynamic: classifier
Dynamic: description
Dynamic: description-content-type
Dynamic: home-page
Dynamic: keywords
Dynamic: license
Dynamic: license-file
Dynamic: provides-extra
Dynamic: requires-dist
Dynamic: requires-python
Dynamic: summary
